{
  "country": "mx",
  "year": 2015,
  "context": "Mexico's 2015 chart was split between international reggaeton dominance and a thriving regional Mexican scene anchored by Banda MS and the late Ariel Camacho's sierreño revolution. 'El Perdón' by Nicky Jam and Enrique Iglesias ruled the year with 30 weeks at number one on Hot Latin Songs. Romeo Santos consolidated his bachata dominance while J Balvin began his ascent to global Latin urban stardom.",
  "tracks": [
    {
      "rank": 1,
      "title": "El Perdón",
      "artist": "Nicky Jam & Enrique Iglesias",
      "albumArt": "https://i.scdn.co/image/ab67616d00001e02b242b4213fb5c21d97dbbf4d",
      "previewUrl": null,
      "spotifyUri": "spotify:track:7qCAVkHWZkF44OzOUKf8Cr",
      "spotifyUrl": "https://open.spotify.com/track/7qCAVkHWZkF44OzOUKf8Cr"
    },
    {
      "rank": 2,
      "title": "Propuesta Indecente",
      "artist": "Romeo Santos",
      "albumArt": "https://i.scdn.co/image/ab67616d00001e02e0e4b48b060715c9aa7fca18",
      "previewUrl": null,
      "spotifyUri": "spotify:track:5PycBIeabfvX3n9ILG7Vrv",
      "spotifyUrl": "https://open.spotify.com/track/5PycBIeabfvX3n9ILG7Vrv"
    },
    {
      "rank": 3,
      "title": "Hilito",
      "artist": "Romeo Santos",
      "albumArt": "https://i.scdn.co/image/ab67616d00001e02e0e4b48b060715c9aa7fca18",
      "previewUrl": null,
      "spotifyUri": "spotify:track:6CKlQHQIxhWtq7MnEJ6QCz",
      "spotifyUrl": "https://open.spotify.com/track/6CKlQHQIxhWtq7MnEJ6QCz"
    },
    {
      "rank": 4,
      "title": "Ay Vamos",
      "artist": "J Balvin",
      "albumArt": "https://i.scdn.co/image/ab67616d00001e024277da4c011dcc87f012bbab",
      "previewUrl": null,
      "spotifyUri": "spotify:track:6Ges5C2IE738iJh4HyQizQ",
      "spotifyUrl": "https://open.spotify.com/track/6Ges5C2IE738iJh4HyQizQ"
    },
    {
      "rank": 5,
      "title": "Ginza",
      "artist": "J Balvin",
      "albumArt": "https://i.scdn.co/image/ab67616d00001e02734b36a0655aae40d78d70f4",
      "previewUrl": null,
      "spotifyUri": "spotify:track:2C2TGgFzrTRIOdQS1vUN5h",
      "spotifyUrl": "https://open.spotify.com/track/2C2TGgFzrTRIOdQS1vUN5h"
    },
    {
      "rank": 6,
      "title": "Lean On",
      "artist": "Major Lazer & DJ Snake feat. MØ",
      "albumArt": "https://i.scdn.co/image/ab67616d00001e021ebfa624d999cf26524bfb90",
      "previewUrl": null,
      "spotifyUri": "spotify:track:0gL7suKdyvMzjm752AQzMd",
      "spotifyUrl": "https://open.spotify.com/track/0gL7suKdyvMzjm752AQzMd"
    },
    {
      "rank": 7,
      "title": "Amor Secreto",
      "artist": "Banda MS de Sergio Lizárraga",
      "albumArt": "https://i.scdn.co/image/ab67616d00001e022c9f13ebe1866ec4c126203c",
      "previewUrl": null,
      "spotifyUri": "spotify:track:7yynBMoPoOnC4nHbF306f9",
      "spotifyUrl": "https://open.spotify.com/track/7yynBMoPoOnC4nHbF306f9"
    },
    {
      "rank": 8,
      "title": "Quiero Más",
      "artist": "Calibre 50",
      "albumArt": "https://i.scdn.co/image/ab67616d00001e0203f11dc561c59440352babd4",
      "previewUrl": null,
      "spotifyUri": "spotify:track:6CmFzaTvg7lRSAWwHmBDfj",
      "spotifyUrl": "https://open.spotify.com/track/6CmFzaTvg7lRSAWwHmBDfj"
    },
    {
      "rank": 9,
      "title": "Volveré a Amarte",
      "artist": "Ariel Camacho y Los Plebes del Rancho",
      "albumArt": "https://i.scdn.co/image/ab67616d00001e02b9966401ab3c67ae2a6c48ee",
      "previewUrl": null,
      "spotifyUri": "spotify:track:0E6g2ECvCoHIGtQTErHLkN",
      "spotifyUrl": "https://open.spotify.com/track/0E6g2ECvCoHIGtQTErHLkN"
    },
    {
      "rank": 10,
      "title": "Want to Want Me",
      "artist": "Jason Derulo",
      "albumArt": "https://i.scdn.co/image/ab67616d00001e02519241bcfc352fc3eaaac5db",
      "previewUrl": null,
      "spotifyUri": "spotify:track:7oGZAicScQt96OAW4AruYy",
      "spotifyUrl": "https://open.spotify.com/track/7oGZAicScQt96OAW4AruYy"
    }
  ],
  "spotifyPlaylistUrl": "https://open.spotify.com/playlist/3Dr3ZgukdVPJW1LGsQWc6s"
}
