{
  "country": "mx",
  "year": 2025,
  "context": "In 2025, corridos tumbados and música mexicana completed their global conquest, with Fuerza Regida and Grupo Frontera placing multiple tracks on international charts while Bad Bunny's DeBÍ TiRAR MáS FOToS dominated Latin music globally. Bad Bunny placed six songs in the Billboard year-end Hot Latin Songs top 10, while Fuerza Regida claimed three spots, cementing Mexican regional music's rise to mainstream powerhouse status.",
  "tracks": [
    {"rank": 1, "title": "DtMF", "artist": "Bad Bunny"},
    {"rank": 2, "title": "BAILE INoLVIDABLE", "artist": "Bad Bunny"},
    {"rank": 3, "title": "NUEVAYoL", "artist": "Bad Bunny"},
    {"rank": 4, "title": "EoO", "artist": "Bad Bunny"},
    {"rank": 5, "title": "ME JALO", "artist": "Fuerza Regida & Grupo Frontera"},
    {"rank": 6, "title": "Tu Boda", "artist": "Óscar Maydon & Fuerza Regida"},
    {"rank": 7, "title": "Loco", "artist": "Netón Vega"},
    {"rank": 8, "title": "Qué Pasaría…", "artist": "Rauw Alejandro & Bad Bunny"},
    {"rank": 9, "title": "VOY A LLeVARTE PA PR", "artist": "Bad Bunny"},
    {"rank": 10, "title": "Por Esos Ojos", "artist": "Fuerza Regida"}
  ]
}
